<?xml version="1.0" encoding="UTF-8"?>
<scene>
	<player x="-3.0" y="1.0" />
	<level>
		<sceneMin x="-3.5" y="-3.0"/>
		<sceneMax x="14.0" y="29.0"/>
		<node x="-5.0" y="-1.0" />
		<node x="-5.0" y="4.0" />
		<node x="0.0" y="4.0" />
		<node x="0.0" y="20.0" />
		<node x="-2.0" y="20.0" />
		<node x="-2.0" y="21.0" />
		<node x="-5.0" y="21.0" />
		<node x="-5.0" y="26.0" />
		<node x="-2.0" y="26.0" />
		<node x="-2.0" y="27.0" />
		<node x="4.0" y="27.0" />
		<node x="4.0" y="25.0" />
		<node x="6.0" y="25.0" />
		<node x="6.0" y="12.0" />
		<node x="4.0" y="12.0" />
		<node x="4.0" y="4.0" />
		<node x="5.5" y="4.0" />
		<node x="5.5" y="-1.0" />
		<node x="4.0" y="-1.0" />
		<node x="4.0" y="-1.5" />
		<node x="-1.0" y="-1.5" />
		<node x="-1.0" y="-1.0" />
	</level>
	<entities>
		<entity x="3.0" y="25.0" name="mushroom" facingRight="true" />
	</entities>
	<sceneLinks>
		<sceneLink linkName="leftUpper" fileName="level1" x="-4.5" y="1.5" halfWidth="0.5" halfHeight="2.5" spawnX="26.0" spawnY="10.0" />
		<sceneLink linkName="leftLower" fileName="level4" x="-4.5" y="23.5" halfWidth="0.5" halfHeight="2.5" spawnX="3.5" spawnY="11.5" />
	</sceneLinks>
	<set>
		<prop name="background" x="7.0" y="5.0" parallax="0.8" depth="-100" />
	</set>
</scene>